COPYING
MANIFEST.in
README.md
requirements.txt
setup.py
review/__init__.py
review/base.py
review/histogram.py
review/scalar.py
rgmining_review.egg-info/PKG-INFO
rgmining_review.egg-info/SOURCES.txt
rgmining_review.egg-info/dependency_links.txt
rgmining_review.egg-info/requires.txt
rgmining_review.egg-info/top_level.txt