Metadata-Version: 1.1
Name: rgmining-review
Version: 0.9.1
Summary: Review data structure for Review graph mining project
Home-page: https://github.com/rgmining/common
Author: Junpei Kawamoto
Author-email: kawamoto.junpei@gmail.com
License: GPLv3
Platform: UNKNOWN
Classifier: Development Status :: 4 - Beta
Classifier: Intended Audience :: Science/Research
Classifier: License :: OSI Approved :: GNU General Public License v3 (GPLv3)
Classifier: Natural Language :: English
Classifier: Programming Language :: Python
Classifier: Topic :: Software Development :: Libraries
Classifier: Topic :: Scientific/Engineering :: Information Analysis
